{
  "case_no": "CL202603180012",
  "product_name": "综合意外医疗保险",
  "claim_type": "意外门诊医疗",
  "current_status": "待审核",
  "source_type": "病历OCR + 系统报案记录 + 补件记录",
  "user_focus": [
    "梳理从出险到补件的时间线",
    "识别时间是否前后一致",
    "补充关键时间间隔"
  ],
  "events": [
    {
      "time": "2026-03-01 18:30",
      "event": "骑车摔伤",
      "source": "出险说明"
    },
    {
      "time": "2026-03-01 20:10",
      "event": "急诊就诊",
      "source": "急诊病历"
    },
    {
      "time": "2026-03-05",
      "event": "客户报案",
      "source": "系统报案记录"
    },
    {
      "time": "2026-03-06",
      "event": "案件受理",
      "source": "系统受理记录"
    },
    {
      "time": "2026-03-08",
      "event": "通知补充费用清单",
      "source": "补件记录"
    },
    {
      "time": "2026-03-15",
      "event": "补交费用清单",
      "source": "材料上传记录"
    }
  ],
  "remarks": "当前可确认出险与首次就医为同日，报案时间晚于出险4天；审核启动时间暂未见明确记录。"
}
